stepcutis/__init__.py
stepcutis/download_models.py
stepcutis/layout.py
stepcutis/ocr.py
stepcutis/paths.py
stepcutis/process_document.py
stepcutis/start.py
stepcutis/projectpackages/CRAFT/__init__.py
stepcutis/projectpackages/CRAFT/craft.py
stepcutis/projectpackages/CRAFT/craft_utils.py
stepcutis/projectpackages/CRAFT/fp16.py
stepcutis/projectpackages/CRAFT/imgproc.py
stepcutis/projectpackages/CRAFT/model.py
stepcutis/projectpackages/CRAFT/refinenet.py
stepcutis/projectpackages/CRAFT/utils.py
stepcutis/projectpackages/CRAFT/basenet/__init__.py
stepcutis/projectpackages/CRAFT/basenet/vgg16_bn.py
stepcutis/projectpackages/LakeOCR/pyproject.toml
stepcutis/projectpackages/LakeOCR/pyvenv.cfg
stepcutis/projectpackages/LakeOCR/GOT/__init__.py
stepcutis/projectpackages/LakeOCR/GOT/data/__init__.py
stepcutis/projectpackages/LakeOCR/GOT/data/base_dataset.py
stepcutis/projectpackages/LakeOCR/GOT/data/conversation_dataset_qwen.py
stepcutis/projectpackages/LakeOCR/GOT/demo/process_results.py
stepcutis/projectpackages/LakeOCR/GOT/demo/run_ocr_2.0.py
stepcutis/projectpackages/LakeOCR/GOT/demo/run_ocr_2.0_crop.py
stepcutis/projectpackages/LakeOCR/GOT/eval/eval_GOT_ocr.py
stepcutis/projectpackages/LakeOCR/GOT/eval/evaluate_GOT.py
stepcutis/projectpackages/LakeOCR/GOT/eval/multi_hardware_eval_GOT.py
stepcutis/projectpackages/LakeOCR/GOT/eval/pyevaltools/__init__.py
stepcutis/projectpackages/LakeOCR/GOT/eval/pyevaltools/eval_ocr.py
stepcutis/projectpackages/LakeOCR/GOT/eval/pyevaltools/eval_ocr_format.py
stepcutis/projectpackages/LakeOCR/GOT/eval/pyevaltools/eval_ocr_scene.py
stepcutis/projectpackages/LakeOCR/GOT/eval/pyevaltools/merge_results.py
stepcutis/projectpackages/LakeOCR/GOT/model/GOT_ocr_2_0.py
stepcutis/projectpackages/LakeOCR/GOT/model/__init__.py
stepcutis/projectpackages/LakeOCR/GOT/model/plug/blip_process.py
stepcutis/projectpackages/LakeOCR/GOT/model/vision_encoder/__init__.py
stepcutis/projectpackages/LakeOCR/GOT/model/vision_encoder/vary_b.py
stepcutis-0.1.1.dist-info/METADATA
stepcutis-0.1.1.dist-info/WHEEL
stepcutis-0.1.1.dist-info/entry_points.txt
stepcutis-0.1.1.dist-info/top_level.txt
stepcutis-0.1.1.dist-info/RECORD
